{
  "frames": {
    "run_0": {
      "frame": {
        "x": 0,
        "y": 0,
        "w": 80,
        "h": 64
      },
      "sourceSize": {
        "w": 80,
        "h": 64
      },
      "spriteSourceSize": {
        "x": 0,
        "y": 0,
        "w": 80,
        "h": 64
      }
    },
    "run_1": {
      "frame": {
        "x": 80,
        "y": 0,
        "w": 80,
        "h": 64
      },
      "sourceSize": {
        "w": 80,
        "h": 64
      },
      "spriteSourceSize": {
        "x": 0,
        "y": 0,
        "w": 80,
        "h": 64
      }
    },
    "run_2": {
      "frame": {
        "x": 160,
        "y": 0,
        "w": 80,
        "h": 64
      },
      "sourceSize": {
        "w": 80,
        "h": 64
      },
      "spriteSourceSize": {
        "x": 0,
        "y": 0,
        "w": 80,
        "h": 64
      }
    },
    "run_3": {
      "frame": {
        "x": 240,
        "y": 0,
        "w": 80,
        "h": 64
      },
      "sourceSize": {
        "w": 80,
        "h": 64
      },
      "spriteSourceSize": {
        "x": 0,
        "y": 0,
        "w": 80,
        "h": 64
      }
    },
    "run_4": {
      "frame": {
        "x": 320,
        "y": 0,
        "w": 80,
        "h": 64
      },
      "sourceSize": {
        "w": 80,
        "h": 64
      },
      "spriteSourceSize": {
        "x": 0,
        "y": 0,
        "w": 80,
        "h": 64
      }
    },
    "run_5": {
      "frame": {
        "x": 400,
        "y": 0,
        "w": 80,
        "h": 64
      },
      "sourceSize": {
        "w": 80,
        "h": 64
      },
      "spriteSourceSize": {
        "x": 0,
        "y": 0,
        "w": 80,
        "h": 64
      }
    },
    "run_6": {
      "frame": {
        "x": 480,
        "y": 0,
        "w": 80,
        "h": 64
      },
      "sourceSize": {
        "w": 80,
        "h": 64
      },
      "spriteSourceSize": {
        "x": 0,
        "y": 0,
        "w": 80,
        "h": 64
      }
    },
    "run_7": {
      "frame": {
        "x": 560,
        "y": 0,
        "w": 80,
        "h": 64
      },
      "sourceSize": {
        "w": 80,
        "h": 64
      },
      "spriteSourceSize": {
        "x": 0,
        "y": 0,
        "w": 80,
        "h": 64
      }
    }
  },
  "animations": {
    "run": [
      "run_0",
      "run_1",
      "run_2",
      "run_3",
      "run_4",
      "run_5",
      "run_6",
      "run_7"
    ]
  },
  "meta": {
    "image": "Mushroom-Run.png",
    "size": {
      "w": 640,
      "h": 64
    }
  }
}